mlboard_client/__init__.py
mlboard_client/encoders.py
mlboard_client/models.py
mlboard_client/py.typed
mlboard_client-0.0.12.dist-info/METADATA
mlboard_client-0.0.12.dist-info/WHEEL
mlboard_client-0.0.12.dist-info/top_level.txt
mlboard_client-0.0.12.dist-info/RECORD
